pymageconverter/__init__.py
pymageconverter/konvesyon.py
pymageconverter-1.0.0.dist-info/METADATA
pymageconverter-1.0.0.dist-info/WHEEL
pymageconverter-1.0.0.dist-info/top_level.txt
pymageconverter-1.0.0.dist-info/RECORD
