Metadata-Version: 2.1
Name: pymageconverter
Version: 1.0.0
Summary: Un projet_collaboration en convertissant un fichier image PNG en JPG et vice versa
Home-page: https://github.com/BlancJorry/PythonL4/
Author: Jorry , Thamar
Author-email: jorryh2@gmail.com
